{
	"id": "1",
	"generation": "0",
	"name": "Gajárszki Réka",
	"gender": "female",
	"birth_place": "private",
	"birth_date": "private",
	"death_date": "private",
	"death_place": "private",
	"marriage_date": "",
	"marriage_place": "",
	"religion": "",
	"comment": "",
	"siblings": [{"sibling_id": "1.0.1","sibling_name": "Gajárszki Roland","sibling_birth_place": "private","sibling_birth_date": "private","sibling_death_place": "private","sibling_death_date": "private","sibling_spouse_name": "private","sibling_marriage_place": "private","sibling_marriage_date": "private"}],
	"children": [{
	"id": "2",
	"generation": "1",
	"name": "Gajárszki Rudolf",
	"gender": "male",
	"birth_place": "private",
	"birth_date": "private",
	"death_date": "private",
	"death_place": "private",
	"marriage_date": "private",
	"marriage_place": "private",
	"religion": "",
	"comment": "",
	"siblings": [],
	"children": [{
		"id": "4",
		"generation": "2",
		"name": "Gajárszky Rudolf István",
		"gender": "male",
		"birth_place": "private",
		"birth_date": "private",
		"death_date": "private",
		"death_place": "private",
		"marriage_date": "private",
		"marriage_place": "private",
		"religion": "",
		"comment": "",
		"siblings": [
			{"sibling_id": "","sibling_name": "","sibling_birth_place": "","sibling_birth_date": "", "sibling_death_place": "","sibling_death_date": "","sibling_spouse_name": "", "sibling_marriage_place": "", "sibling_marriage_date": ""}
		],
		"children": [{
			"id": "8",
			"generation": "3",
			"name": "Gajárszki Rudolf Rafael",
			"gender": "male",
			"birth_place": "Tárnok",
			"birth_date": "1906.04.17",
			"death_date": "1974.?.?",
			"death_place": "Székesfehérvár",
			"marriage_date": "1931.09.26",
			"marriage_place": "Székesfehérvár",
			"religion": "katolikus",
			"comment": "Testvére Gajárszki István, 1935-ben Galántai-ra változtatta vezetéknevét (u.b. 149/1935).",
			"siblings": [
				{"sibling_id": "12.3.1","sibling_name": "Gajárszki Ferenc","sibling_birth_place": "Székesfehérvár","sibling_birth_date": "1911.09.22", "sibling_death_place": "?","sibling_death_date": "1982(?)","sibling_spouse_name": "Liszi Mária", "sibling_marriage_place": "Székesfehérvár", "sibling_marriage_date": "1935.09.21"},
				{"sibling_id": "12.3.2","sibling_name": "Gajárszki István","sibling_birth_place": "Székesfehérvár","sibling_birth_date": "1909.11.15", "sibling_death_place": "?","sibling_death_date": "1978(?)","sibling_spouse_name": "?", "sibling_marriage_place": "", "sibling_marriage_date": ""},
				{"sibling_id": "12.3.3","sibling_name": "Gajárszki Imre","sibling_birth_place": "Székesfehérvár","sibling_birth_date": "1914.07.07", "sibling_death_place": "Budapest(?)","sibling_death_date": "1963.07.17","sibling_spouse_name": "?", "sibling_marriage_place": "", "sibling_marriage_date": ""},
				{"sibling_id": "12.3.4","sibling_name": "Gajárszki István József","sibling_birth_place": "Tárnok","sibling_birth_date": "1908.07.?", "sibling_death_place": "Tárnok","sibling_death_date": "1908.08.19","sibling_spouse_name": "", "sibling_marriage_place": "", "sibling_marriage_date": ""}
			],
			"children": [{
				"id": "16",
				"generation": "4",
				"name": "Gajárszki István",
				"gender": "male",
				"birth_place": "Tárnok",
				"birth_date": "1882.08.08",
				"death_date": "?",
				"death_place": "?",
				"marriage_date": "1908.05.20",
				"marriage_place": "Tárnok",
				"religion": "katolikus",
				"comment": "",
				"siblings": [
					{"sibling_id": "16.4.1","sibling_name": "Gajárszky István","sibling_birth_place": "Tárnok","sibling_birth_date": "1878.08.11", "sibling_death_place": "Tárnok","sibling_death_date": "1879.04.15","sibling_spouse_name": "", "sibling_marriage_place": "", "sibling_marriage_date": ""},
					{"sibling_id": "16.4.2","sibling_name": "Gajárszky János","sibling_birth_place": "Tárnok","sibling_birth_date": "1880.12.14", "sibling_death_place": "?","sibling_death_date": "1944.01.07","sibling_spouse_name": "?", "sibling_marriage_place": "?", "sibling_marriage_date": "?"},
					{"sibling_id": "16.4.3","sibling_name": "Gajárszky József","sibling_birth_place": "Tárnok","sibling_birth_date": "1884.03.13", "sibling_death_place": "?","sibling_death_date": "?","sibling_spouse_name": "Gadró Teréz", "sibling_marriage_place": "Tárnok", "sibling_marriage_date": "1908.11.17"},
					{"sibling_id": "16.4.4","sibling_name": "Gajárszky Mária","sibling_birth_place": "Tárnok","sibling_birth_date": "1886.04.15", "sibling_death_place": "Tárnok","sibling_death_date": "1889.11.27","sibling_spouse_name": "", "sibling_marriage_place": "", "sibling_marriage_date": ""},
					{"sibling_id": "16.4.5","sibling_name": "Gajárszki Ferenc","sibling_birth_place": "Tárnok","sibling_birth_date": "1888.01.29", "sibling_death_place": "Tárnok","sibling_death_date": "1890.04.18","sibling_spouse_name": "", "sibling_marriage_place": "", "sibling_marriage_date": ""},
					{"sibling_id": "16.4.6","sibling_name": "Gajárszki Erzsébet","sibling_birth_place": "Tárnok","sibling_birth_date": "1889.11.17", "sibling_death_place": "?","sibling_death_date": "?","sibling_spouse_name": "?", "sibling_marriage_place": "?", "sibling_marriage_date": "?"},
					{"sibling_id": "16.4.7","sibling_name": "Gajárszki Mária","sibling_birth_place": "Tárnok","sibling_birth_date": "1891.04.12", "sibling_death_place": "Tárnok","sibling_death_date": "1891.06.14","sibling_spouse_name": "", "sibling_marriage_place": "", "sibling_marriage_date": ""}

				],
				"children": [{
					"id": "32",
					"generation": "5",
					"name": "Gajárszky János",
					"gender": "male",
					"birth_place": "Tárnok",
					"birth_date": "1855.10.15",
					"death_date": "1902.06.08",
					"death_place": "Tárnok",
					"marriage_date": "1878.02.06",
					"marriage_place": "Tárnok",
					"religion": "katolikus",
					"comment": "foglalkozása: kisbirtokos, vízkorban hunyt el, 2. felesége Huskovics Katalin",
					"siblings": [
						{"sibling_id": "32.5.1","sibling_name": "Gajárszky Lukács","sibling_birth_place": "Tárnok","sibling_birth_date": "1843.01.09", "sibling_death_place": "?","sibling_death_date": "?","sibling_spouse_name": "?", "sibling_marriage_place": "?", "sibling_marriage_date": "?"},
						{"sibling_id": "32.5.2","sibling_name": "Gajárszky Ilona","sibling_birth_place": "Tárnok","sibling_birth_date": "1845.03.31", "sibling_death_place": "?","sibling_death_date": "?","sibling_spouse_name": "?", "sibling_marriage_place": "?", "sibling_marriage_date": "?"},
						{"sibling_id": "32.5.3","sibling_name": "Gajárszky András","sibling_birth_place": "Tárnok","sibling_birth_date": "1847.11.12", "sibling_death_place": "?","sibling_death_date": "?","sibling_spouse_name": "?", "sibling_marriage_place": "?", "sibling_marriage_date": "?"},
						{"sibling_id": "32.5.4","sibling_name": "Gajárszky Magdolna","sibling_birth_place": "Tárnok","sibling_birth_date": "1851.02.22", "sibling_death_place": "?","sibling_death_date": "?","sibling_spouse_name": "?", "sibling_marriage_place": "?", "sibling_marriage_date": "?"}
					],
					"children": [						{
                        "id": "64",
                        "generation": "6",
                        "name": "Gajárszky József",
                        "gender": "male",
                        "birth_place": "Tárnok",
                        "birth_date": "1816.10.27",
                        "death_date": "1857.01.04",
                        "death_place": "Tárnok",
                        "marriage_date": "1841.11.03",
                        "marriage_place": "Tárnok",
                        "religion": "katolikus",
                        "comment": "",
                        "siblings": [
                        ],
                        "children": [						{
							"id": "128",
							"generation": "7",
							"name": "Gajárszky János",
							"gender": "male",
							"birth_place": "?",
							"birth_date": "?",
							"death_date": "?",
							"death_place": "?",
							"marriage_date": "?",
							"marriage_place": "?",
							"religion": "katolikus",
							"comment": "",
							"siblings": [
							],
							"children": []
						},{
							"id": "129",
							"generation": "7",
							"name": "Mária",
							"gender": "female",
							"birth_place": "?",
							"birth_date": "?",
							"death_date": "?",
							"death_place": "?",
							"marriage_date": "?",
							"marriage_place": "?",
							"religion": "katolikus",
							"comment": "",
							"siblings": [
							],
							"children": []
						}]
                    },{
                        "id": "65",
                        "generation": "6",
                        "name": "Szabó Erzsébet",
                        "gender": "female",
                        "birth_place": "Tárnok",
                        "birth_date": "1821.11.21",
                        "death_date": "1867.01.07",
                        "death_place": "Tárnok",
                        "marriage_date": "1841.11.03",
                        "marriage_place": "Tárnok",
                        "religion": "katolikus",
                        "comment": "",
                        "siblings": [
                        ],
                        "children": [						{
							"id": "130",
							"generation": "7",
							"name": "Szabó János",
							"gender": "male",
							"birth_place": "?",
							"birth_date": "?",
							"death_date": "?",
							"death_place": "?",
							"marriage_date": "?",
							"marriage_place": "?",
							"religion": "katolikus",
							"comment": "",
							"siblings": [
							],
							"children": []
						},{
							"id": "131",
							"generation": "7",
							"name": "Erzsébet",
							"gender": "female",
							"birth_place": "?",
							"birth_date": "?",
							"death_date": "?",
							"death_place": "?",
							"marriage_date": "?",
							"marriage_place": "?",
							"religion": "katolikus",
							"comment": "",
							"siblings": [
							],
							"children": []
						}]
                    }]
				},{
					"id": "33",
					"generation": "5",
					"name": "Kovács Anna",
					"gender": "female",
					"birth_place": "Tárnok",
					"birth_date": "1860.03.21",
					"death_date": "1891.08.07",
					"death_place": "Tárnok",
					"marriage_date": "1878.02.06",
					"marriage_place": "Tárnok",
					"religion": "katolikus",
					"comment": "",
					"siblings": [
					],
					"children": [
						{
							"id": "66",
							"generation": "6",
							"name": "Kovács György",
							"gender": "male",
							"birth_place": "?",
							"birth_date": "?",
							"death_date": "?",
							"death_place": "?",
							"marriage_date": "?",
							"marriage_place": "?",
							"religion": "katolikus",
							"comment": "",
							"siblings": [
							],
							"children": []
						},{
							"id": "67",
							"generation": "6",
							"name": "Bilik Anna",
							"gender": "female",
							"birth_place": "?",
							"birth_date": "?",
							"death_date": "?",
							"death_place": "?",
							"marriage_date": "?",
							"marriage_place": "?",
							"religion": "katolikus",
							"comment": "",
							"siblings": [
							],
							"children": []
						}
					]
				}]
			},{
				"id": "17",
				"generation": "4",
				"name": "Viczing Johanna",
				"gender": "female",
				"birth_place": "Tárnok",
				"birth_date": "1885.05.23",
				"death_date": "?",
				"death_place": "?",
				"marriage_date": "1908.05.20",
				"marriage_place": "Tárnok",
				"religion": "katolikus",
				"comment": "",
				"siblings": [
					{"sibling_id": "17.4.1","sibling_name": "Viczing Anna","sibling_birth_place": "Tárnok","sibling_birth_date": "1887.10.24", "sibling_death_place": "Tárnok","sibling_death_date": "1892.12.14","sibling_spouse_name": "", "sibling_marriage_place": "", "sibling_marriage_date": ""},
					{"sibling_id": "17.4.2","sibling_name": "Viczing János","sibling_birth_place": "Tárnok","sibling_birth_date": "1891.06.24", "sibling_death_place": "Tárnok","sibling_death_date": "1974.11.12","sibling_spouse_name": "Gajárszki Katalin", "sibling_marriage_place": "Tárnok", "sibling_marriage_date": "1920.04.29"},
					{"sibling_id": "17.4.3","sibling_name": "Viczing Irén","sibling_birth_place": "Tárnok","sibling_birth_date": "1895.06.28", "sibling_death_place": "?","sibling_death_date": "?","sibling_spouse_name": "Jámbor Gyula", "sibling_marriage_place": "Tárnok", "sibling_marriage_date": "1920.04.29"},
					{"sibling_id": "17.4.4","sibling_name": "Viczing Anna","sibling_birth_place": "Tárnok","sibling_birth_date": "1898", "sibling_death_place": "Tárnok","sibling_death_date": "1900.03.02","sibling_spouse_name": "", "sibling_marriage_place": "", "sibling_marriage_date": ""}
				],
				"children": [{
					"id": "34",
					"generation": "5",
					"name": "Viczing János",
					"gender": "male",
					"birth_place": "Tárnok",
					"birth_date": "1855.08.14",
					"death_date": "1922.04.01",
					"death_place": "Tárnok",
					"marriage_date": "?",
					"marriage_place": "?",
					"religion": "katolikus",
					"comment": "foglalkozása: kocsmáros, gutaütésben hunyt el 67 évesen",
					"siblings": [
					],
					"children": [{
						"id": "68",
						"generation": "6",
						"name": "Viczing János",
						"gender": "male",
						"birth_place": "?",
						"birth_date": "?",
						"death_date": "?",
						"death_place": "?",
						"marriage_date": "?",
						"marriage_place": "?",
						"religion": "",
						"comment": "",
						"siblings": [
						],
						"children": []
					},{
						"id": "69",
						"generation": "6",
						"name": "Bilár Katalin",
						"gender": "female",
						"birth_place": "?",
						"birth_date": "?",
						"death_date": "?",
						"death_place": "?",
						"marriage_date": "?",
						"marriage_place": "?",
						"religion": "?",
						"comment": "",
						"siblings": [
						],
						"children": []
					}]
				},{
					"id": "35",
					"generation": "5",
					"name": "Ábel Katalin",
					"gender": "female",
					"birth_place": "?",
					"birth_date": "?",
					"death_date": "?",
					"death_place": "?",
					"marriage_date": "?",
					"marriage_place": "?",
					"religion": "katolikus",
					"comment": "",
					"siblings": [
					],
					"children": []
				}]
			}]
		},{
			"id": "9",
			"generation": "3",
			"name": "Fister Mária",
			"gender": "female",
			"birth_place": "Székesfehérvár",
			"birth_date": "1909.08.16",
			"death_date": "1988.?.?",
			"death_place": "Székesfehérvár",
			"marriage_date": "1931.09.26",
			"marriage_place": "Székesfehérvár",
			"religion": "katolikus",
			"comment": "",
			"siblings": [
			],
			"children": [{
				"id": "18",
				"generation": "4",
				"name": "Fister György",
				"gender": "male",
				"birth_place": "Székesfehérvár",
				"birth_date": "1881.04.28",
				"death_date": "1965",
				"death_place": "?",
				"marriage_date": "1908.10.11",
				"marriage_place": "Székesfehérvár",
				"religion": "katolikus",
				"comment": "",
				"siblings": [
					{"sibling_id": "18.4.1","sibling_name": "Fister Erzsébet","sibling_birth_place": "Székesfehérvár","sibling_birth_date": "1884.11.02", "sibling_death_place": "?","sibling_death_date": "?","sibling_spouse_name": "", "sibling_marriage_place": "", "sibling_marriage_date": ""},
					{"sibling_id": "18.4.2","sibling_name": "Fister István","sibling_birth_place": "Székesfehérvár","sibling_birth_date": "1891.08.28", "sibling_death_place": "?","sibling_death_date": "?","sibling_spouse_name": "", "sibling_marriage_place": "", "sibling_marriage_date": ""}
				],
				"children": [
					{
						"id": "36",
						"generation": "5",
						"name": "Fister Ferenc",
						"gender": "male",
						"birth_place": "?",
						"birth_date": "?",
						"death_date": "?",
						"death_place": "?",
						"marriage_date": "?",
						"marriage_place": "?",
						"religion": "",
						"comment": "",
						"siblings": [
						],
						"children": []
					},{
						"id": "37",
						"generation": "5",
						"name": "Peresztegi Nagy Borbála",
						"gender": "female",
						"birth_place": "?",
						"birth_date": "?",
						"death_date": "?",
						"death_place": "?",
						"marriage_date": "?",
						"marriage_place": "?",
						"religion": "",
						"comment": "",
						"siblings": [
						],
						"children": []
					}
				]
			},{
				"id": "19",
				"generation": "4",
				"name": "Hegedüs Anna",
				"gender": "female",
				"birth_place": "Székesfehérvár",
				"birth_date": "1887.04.27",
				"death_date": "1959.09.01",
				"death_place": "Székesfehérvár",
				"marriage_date": "1908.10.11",
				"marriage_place": "Székesfehévár",
				"religion": "katolikus",
				"comment": "",
				"siblings": [
					{"sibling_id": "19.4.1","sibling_name": "Hegedüs Erzsébet","sibling_birth_place": "Székesfehérvár","sibling_birth_date": "1885.11.12", "sibling_death_place": "?","sibling_death_date": "?","sibling_spouse_name": "?", "sibling_marriage_place": "?", "sibling_marriage_date": "?"},
					{"sibling_id": "19.4.2","sibling_name": "Hegedüs Ferenc","sibling_birth_place": "Székesfehérvár","sibling_birth_date": "1888.11.25", "sibling_death_place": "?","sibling_death_date": "?","sibling_spouse_name": "?", "sibling_marriage_place": "?", "sibling_marriage_date": "?"},
					{"sibling_id": "19.4.3","sibling_name": "Hegedüs Teréz","sibling_birth_place": "Székesfehérvár","sibling_birth_date": "1890.10.14", "sibling_death_place": "?","sibling_death_date": "?","sibling_spouse_name": "?", "sibling_marriage_place": "?", "sibling_marriage_date": "?"},
					{"sibling_id": "19.4.4","sibling_name": "Hegedüs Mária","sibling_birth_place": "Székesfehérvár","sibling_birth_date": "1891.09.02", "sibling_death_place": "?","sibling_death_date": "?","sibling_spouse_name": "?", "sibling_marriage_place": "?", "sibling_marriage_date": "?"},
					{"sibling_id": "19.4.5","sibling_name": "Hegedüs György","sibling_birth_place": "Székesfehérvár","sibling_birth_date": "1894.10.28", "sibling_death_place": "?","sibling_death_date": "?","sibling_spouse_name": "?", "sibling_marriage_place": "?", "sibling_marriage_date": "?"}
				],
				"children": [{
					"id": "38",
					"generation": "5",
					"name": "Hegedüs György",
					"gender": "male",
					"birth_place": "?",
					"birth_date": "?",
					"death_date": "?",
					"death_place": "?",
					"marriage_date": "?",
					"marriage_place": "?",
					"religion": "",
					"comment": "",
					"siblings": [
					],
					"children": []
				},{
					"id": "39",
					"generation": "5",
					"name": "Nagy Anna",
					"gender": "female",
					"birth_place": "?",
					"birth_date": "?",
					"death_date": "?",
					"death_place": "?",
					"marriage_date": "?",
					"marriage_place": "?",
					"religion": "",
					"comment": "",
					"siblings": [
					],
					"children": []
				}]
			}]
		}]
	},{
		"id": "5",
		"generation": "2",
		"name": "Káldi Rozália",
		"gender": "female",
		"birth_place": "private",
		"birth_date": "private",
		"death_date": "private",
		"death_place": "private",
		"marriage_date": "private",
		"marriage_place": "private",
		"religion": "",
		"comment": "",
		"siblings": [
		],
		"children": [{
			"id": "10",
			"generation": "3",
			"name": "Káldi Pál",
			"gender": "male",
			"birth_place": "Alsóújlak",
			"birth_date": "1895.01.16",
			"death_date": "1963.07.24",
			"death_place": "Alsóújlak",
			"marriage_date": "1928.09.30",
			"marriage_place": "Kám",
			"religion": "katolikus",
			"comment": "",
			"siblings": [
				{"sibling_id": "10.3.1","sibling_name": "Káldi József","sibling_birth_place": "Kám","sibling_birth_date": "1887.11.27", "sibling_death_place": "?","sibling_death_date": "?","sibling_spouse_name": "?", "sibling_marriage_place": "?", "sibling_marriage_date": "?"},
				{"sibling_id": "10.3.2","sibling_name": "Káldi Pál","sibling_birth_place": "Kám","sibling_birth_date": "1890.06.16", "sibling_death_place": "Kám","sibling_death_date": "1893.06.01","sibling_spouse_name": "?", "sibling_marriage_place": "?", "sibling_marriage_date": "?"},
				{"sibling_id": "10.3.3","sibling_name": "Káldi Antal","sibling_birth_place": "Kám","sibling_birth_date": "1892.10.28", "sibling_death_place": "?","sibling_death_date": "?","sibling_spouse_name": "?", "sibling_marriage_place": "?", "sibling_marriage_date": "?"},
				{"sibling_id": "10.3.4","sibling_name": "Káldi Péter","sibling_birth_place": "Kám","sibling_birth_date": "1902.06.26", "sibling_death_place": "Alsóújlak","sibling_death_date": "1940.10.25","sibling_spouse_name": "?", "sibling_marriage_place": "?", "sibling_marriage_date": "?"}
			],
			"children": [{
				"id": "20",
				"generation": "4",
				"name": "Káldi János",
				"gender": "male",
				"birth_place": "?",
				"birth_date": "1857(?)",
				"death_date": "1917.01.02",
				"death_place": "Alsóújlak",
				"marriage_date": "1886.06.17",
				"marriage_place": "Csehimidszent",
				"religion": "katolikus",
				"comment": "",
				"siblings": [
				],
				"children": [{
					"id": "40",
					"generation": "5",
					"name": "Káldi József",
					"gender": "male",
					"birth_place": "?",
					"birth_date": "?",
					"death_date": "?",
					"death_place": "?",
					"marriage_date": "?",
					"marriage_place": "?",
					"religion": "",
					"comment": "",
					"siblings": [
					],
					"children": []
				},{
					"id": "41",
					"generation": "5",
					"name": "Takáts Rozália",
					"gender": "female",
					"birth_place": "?",
					"birth_date": "?",
					"death_date": "?",
					"death_place": "?",
					"marriage_date": "?",
					"marriage_place": "?",
					"religion": "",
					"comment": "Fia, Káldi János esküvőjén Takáts, viszont Káldi János halálánál Sós vezetéknéven említik.",
					"siblings": [
					],
					"children": []
				}]
			},{
				"id": "21",
				"generation": "4",
				"name": "Mátyás Borbála",
				"gender": "female",
				"birth_place": "Csehimindszent",
				"birth_date": "1866.10.20",
				"death_date": "?",
				"death_place": "?",
				"marriage_date": "1886.06.17",
				"marriage_place": "Csehimidszent",
				"religion": "",
				"comment": "",
				"siblings": [
				],
				"children": [{
					"id": "42",
					"generation": "5",
					"name": "Mátyás Antal",
					"gender": "male",
					"birth_place": "?",
					"birth_date": "?",
					"death_date": "?",
					"death_place": "?",
					"marriage_date": "?",
					"marriage_place": "?",
					"religion": "",
					"comment": "",
					"siblings": [
					],
					"children": []
				},{
					"id": "43",
					"generation": "5",
					"name": "Góczán Katalin",
					"gender": "female",
					"birth_place": "?",
					"birth_date": "?",
					"death_date": "?",
					"death_place": "?",
					"marriage_date": "?",
					"marriage_place": "?",
					"religion": "",
					"comment": "",
					"siblings": [
					],
					"children": []
				}]
			}]
		},{
			"id": "11",
			"generation": "3",
			"name": "Nagy Rozália",
			"gender": "female",
			"birth_place": "Alsóújlak",
			"birth_date": "1901.10.20",
			"death_date": "1989(?)",
			"death_place": "Alsóújlak",
			"marriage_date": "1928.09.30",
			"marriage_place": "Alsóújlak",
			"religion": "katolikus",
			"comment": "",
			"siblings": [
			],
			"children": [{
				"id": "22",
				"generation": "4",
				"name": "Nagy János",
				"gender": "male",
				"birth_place": "?",
				"birth_date": "?",
				"death_date": "?",
				"death_place": "?",
				"marriage_date": "?",
				"marriage_place": "?",
				"religion": "",
				"comment": "",
				"siblings": [
				],
				"children": []
			},{
				"id": "23",
				"generation": "4",
				"name": "Horváth Julianna",
				"gender": "female",
				"birth_place": "?",
				"birth_date": "?",
				"death_date": "?",
				"death_place": "?",
				"marriage_date": "?",
				"marriage_place": "?",
				"religion": "",
				"comment": "",
				"siblings": [
				],
				"children": []
			}]
		}]
	}]
},{
	"id": "3",
	"generation": "1",
	"name": "Velegi Erika",
	"gender": "female",
	"birth_place": "private",
	"birth_date": "private",
	"death_date": "private",
	"death_place": "private",
	"marriage_date": "private",
	"marriage_place": "private",
	"religion": "",
	"comment": "",
	"siblings": [{"sibling_id": "3.1.1","sibling_name": "Velegi Lajos","sibling_birth_place": "private","sibling_birth_date": "private","sibling_death_place": "private","sibling_death_date": "private","sibling_spouse_name": "private","sibling_marriage_place": "private","sibling_marriage_date": "private"}],
	"children": [{
		"id": "6",
		"generation": "2",
		"name": "Velegi Lajos",
		"gender": "male",
		"birth_place": "private",
		"birth_date": "private",
		"death_date": "private",
		"death_place": "private",
		"marriage_date": "private",
		"marriage_place": "private",
		"religion": "",
		"comment": "",
		"siblings": [
		],
		"children": []
	},{
		"id": "7",
		"generation": "2",
		"name": "Zsilovics Mária Magdolna",
		"gender": "female",
		"birth_place": "private",
		"birth_date": "private",
		"death_date": "private",
		"death_place": "private",
		"marriage_date": "private",
		"marriage_place": "private",
		"religion": "",
		"comment": "",
		"siblings": [
		],
		"children": []
	}]
}]
}